cityview/__init__.py
cityview/layers/__init__.py
cityview/layers/base.py
cityview/layers/cityjson.py
cityview/static/widget.css
cityview/static/widget.js
cityview/view.py
cityview-0.2.0.dist-info/LICENSE.txt
cityview-0.2.0.dist-info/METADATA
cityview-0.2.0.dist-info/WHEEL
cityview-0.2.0.dist-info/RECORD
