Metadata-Version: 2.1
Name: cityview
Version: 0.2.0
Summary: CityJSON renderer for Jupyter Notebook / JupyterLab
Home-page: https://github.com/ozekik/cityview/
License: MIT
Author: Kentaro Ozeki
Author-email: 32771324+ozekik@users.noreply.github.com
Requires-Python: >=3.9,<4.0
Classifier: License :: OSI Approved :: MIT License
Classifier: Programming Language :: Python :: 3
Classifier: Programming Language :: Python :: 3.9
Classifier: Programming Language :: Python :: 3.10
Classifier: Programming Language :: Python :: 3.11
Classifier: Programming Language :: Python :: 3.12
Requires-Dist: anywidget[dev] (>=0.9.13,<0.10.0)
Project-URL: Repository, https://github.com/ozekik/cityview
